xir/__init__.py
xir/bonsai.py
xir/constraint.py
xir/unit.py
xir/xir.py
xir/viz/__init__.py
xir/viz/d3_lib.py
xir/viz/viz.py
xir/viz/css/force_directed_graph.css
xir/viz/d3/LICENSE
xir/viz/d3/d3.v4.js
xir/viz/d3/d3.v4.min.js
xir/viz/d3/require.js
xir/viz/js/structural.js
xir-0.0.3.dist-info/LICENSE
xir-0.0.3.dist-info/METADATA
xir-0.0.3.dist-info/WHEEL
xir-0.0.3.dist-info/top_level.txt
xir-0.0.3.dist-info/RECORD
